messaging_middleware/__init__.py
messaging_middleware/Logger/DefaultLogger.py
messaging_middleware/Logger/Logger 2.py
messaging_middleware/Logger/Logger.py
messaging_middleware/Logger/__init__ 2.py
messaging_middleware/Logger/__init__.py
messaging_middleware/avro_communication_layer/Producer.py
messaging_middleware/avro_communication_layer/__init__.py
messaging_middleware/configuration/__init__.py
messaging_middleware/confluent_producer/AVROProducer.py
messaging_middleware/confluent_producer/ConfluentProducer.py
messaging_middleware/confluent_producer/Producer.py
messaging_middleware/confluent_producer/__init__.py
messaging_middleware/kafka_communication_layer/Producer.py
messaging_middleware/kafka_communication_layer/__init__.py
messaging_middleware/tests/__init__.py
messaging_middleware/tests/producers.py
messaging_middleware/utils/__init__.py
messaging_middleware/utils/filesystem.py
messaging_middleware/utils/logger.py
microservices_messaging_layer-1.0.22.dist-info/LICENSE.txt
microservices_messaging_layer-1.0.22.dist-info/METADATA
microservices_messaging_layer-1.0.22.dist-info/WHEEL
microservices_messaging_layer-1.0.22.dist-info/top_level.txt
microservices_messaging_layer-1.0.22.dist-info/RECORD
