Metadata-Version: 2.1
Name: microservices-messaging-layer
Version: 1.0.22
Summary: Messaging Communication Layer for Microservices Architecture
Home-page: https://github.com/antoniodimariano/kafka_messaging_layer
Author: Antonio Di Mariano
Author-email: antonio.dimariano@gmail.com
License: UNKNOWN
Platform: UNKNOWN
Classifier: Programming Language :: Python :: 3
Classifier: License :: OSI Approved :: MIT License
Classifier: Operating System :: OS Independent
Requires-Python: ~=3.6
Requires-Dist: avro-python3
Requires-Dist: kafka
Requires-Dist: requests
Requires-Dist: confluent-kafka
